[
  {
    "Type": "RecipeData",
    "Name": "RECIPE_Tool_FishingRod_Maple",
    "Class": "UScriptClass'RecipeData'",
    "Flags": "RF_Public | RF_Standalone | RF_Transactional | RF_WasLoaded | RF_LoadCompleted",
    "Properties": {
      "ItemsConsumed": [
        {
          "ItemData": {
            "ObjectName": "FuelItemData'ITEM_Resources_Wood_Maple'",
            "ObjectPath": "RSDragonwilds/Content/Gameplay/Items/Resources/Wood/ITEM_Resources_Wood_Maple.0"
          },
          "Count": 1
        },
        {
          "ItemData": {
            "ObjectName": "ItemData'ITEM_Resources_Thread_Mystic'",
            "ObjectPath": "RSDragonwilds/Content/Gameplay/Items/Resources/ITEM_Resources_Thread_Mystic.0"
          },
          "Count": 1
        },
        {
          "ItemData": {
            "ObjectName": "ItemData'ITEM_Resources_MithrilBar'",
            "ObjectPath": "RSDragonwilds/Content/Gameplay/Items/Resources/Metal/ITEM_Resources_MithrilBar.0"
          },
          "Count": 1
        }
      ],
      "ItemsCreated": [
        {
          "ItemData": {
            "ObjectName": "FishingRodHeldEquipmentData'ITEM_FishingRod_Maple'",
            "ObjectPath": "/Fishing/Gameplay/Character/Player/Equipment/Held/FishingRod/ITEM_FishingRod_Maple"
          },
          "Count": 1
        }
      ],
      "AudioTag": {
        "TagName": "Audio.Fishing.Rod"
      },
      "SkillUsedToCraft": {
        "ObjectName": "SkillData'SKILL_Artisan'",
        "ObjectPath": "RSDragonwilds/Content/Gameplay/Character/Player/Skills/SKILL_Artisan.1"
      },
      "OnCraftXpEvent": {
        "DataTable": {
          "ObjectName": "DataTable'DT_XPEvents_Crafting'",
          "ObjectPath": "RSDragonwilds/Content/Gameplay/Progress/XPEventTables/DT_XPEvents_Crafting.0"
        },
        "RowName": "Craft_Crafting_Table_Recipe_Tier1"
      },
      "SkillXPAwardedOnCraft": 15,
      "PersistenceID": "weYW-UGf-s9Iq8mBC_sJWA",
      "InternalName": "recipe_fishingrod_maple"
    }
  }
]