[
  {
    "Type": "RecipeData",
    "Name": "RECIPE_MagicFocus",
    "Class": "UScriptClass'RecipeData'",
    "Flags": "RF_Public | RF_Standalone | RF_Transactional | RF_WasLoaded | RF_LoadCompleted",
    "Properties": {
      "ItemsConsumed": [
        {
          "ItemData": {
            "ObjectName": "ItemData'ITEM_Resources_WildAnima'",
            "ObjectPath": "RSDragonwilds/Content/Gameplay/Items/Resources/Magic/ITEM_Resources_WildAnima.0"
          },
          "Count": 1
        },
        {
          "ItemData": {
            "ObjectName": "ItemData'ITEM_Resources_Stone'",
            "ObjectPath": "RSDragonwilds/Content/Gameplay/Items/Resources/Mineral/ITEM_Resources_Stone.0"
          },
          "Count": 10
        }
      ],
      "ItemsCreated": [
        {
          "ItemData": {
            "ObjectName": "WhetstoneItemData'ITEM_Consumable_MagicFocus'",
            "ObjectPath": "RSDragonwilds/Content/Gameplay/Items/Consumables/Misc/ITEM_Consumable_MagicFocus.0"
          },
          "Count": 1
        }
      ],
      "AudioTag": {
        "TagName": "Audio.Stone"
      },
      "OnCraftXpEvent": {
        "DataTable": {
          "ObjectName": "DataTable'DT_XPEvents_Crafting'",
          "ObjectPath": "RSDragonwilds/Content/Gameplay/Progress/XPEventTables/DT_XPEvents_Crafting.0"
        },
        "RowName": "Craft_Crafting_Table_Recipe_Tier1"
      },
      "PersistenceID": "gW7MckUhyvcoOkGCwBOFeg",
      "InternalName": "RECIPE_Consumable_MagicFocus"
    }
  }
]