[
  {
    "Type": "RecipeData",
    "Name": "RECIPE_Armour_T0_Cape_PinkDyad",
    "Class": "UScriptClass'RecipeData'",
    "Flags": "RF_Public | RF_Standalone | RF_Transactional | RF_WasLoaded | RF_LoadCompleted",
    "Properties": {
      "ItemsCreated": [
        {
          "ItemData": {
            "ObjectName": "WearableEquipmentData'ITEM_Cape_PinkDyad'",
            "ObjectPath": "/DowdunReach/Gameplay/Character/Player/Equipment/Cape/ITEM_Cape_PinkDyad"
          },
          "Count": 1
        }
      ],
      "AudioTag": {
        "TagName": "Audio.Cloth"
      },
      "SkillUsedToCraft": {
        "ObjectName": "SkillData'SKILL_Artisan'",
        "ObjectPath": "RSDragonwilds/Content/Gameplay/Character/Player/Skills/SKILL_Artisan.1"
      },
      "SkillXPAwardedOnCraft": 0,
      "PersistenceID": "xUaZYU0U43lFX6KDxgy_sQ",
      "InternalName": "recipe_armour_t0_cape_PinkDyad"
    }
  }
]